PyCDTS-0.2.0.data/scripts/cdts.py
pycdts/Berfun.py
pycdts/DAE_DS_ber.py
pycdts/DAE_PS.py
pycdts/Database.py
pycdts/FOP_Gummel.py
pycdts/Newton_DS_ber.py
pycdts/Newton_PS.py
pycdts/NumericalEngine.py
pycdts/OPS_Gummel.py
pycdts/PVRD.py
pycdts/PVRD_DialogBox.py
pycdts/PVRD_GraphicsItems.py
pycdts/PVRD_ModeWidgets.py
pycdts/PVRD_ProjectWidget.py
pycdts/PVRD_mesh_rect.py
pycdts/PVRD_models.py
pycdts/PVRD_pkgTest.py
pycdts/PVRD_projectContainer.py
pycdts/PVRD_pyqtOpenGL.py
pycdts/Project.py
pycdts/Structure.py
pycdts/Test_demo.py
pycdts/__init__.py
pycdts/algorithm.py
pycdts/damping_PS.py
pycdts/diffusionSolver.py
pycdts/generalFunctions.py
pycdts/latexQLabel.py
pycdts/latexQWidget.py
pycdts/linearized_PS.py
pycdts/mesh_class.py
pycdts/poissonSolver.py
pycdts/reactionSolver.py
pycdts/resources.py
pycdts/simpleLinearized_PS.py
pycdts/simple_PS.py
pycdts/simul_DS.py
pycdts/simul_DS_ber.py
pycdts/simul_DS_ber_FOP.py
pycdts/simul_RS.py
pycdts/simul_RS2.py
pycdts/simul_RS2_FOP.py
pycdts/solutionBrowser.py
pycdts/solver.py
pycdts/test.py
pycdts/test/__init__.py
PyCDTS-0.2.0.dist-info/LICENSE.txt
PyCDTS-0.2.0.dist-info/METADATA
PyCDTS-0.2.0.dist-info/WHEEL
PyCDTS-0.2.0.dist-info/top_level.txt
PyCDTS-0.2.0.dist-info/RECORD
